main.py
ap2_sdk-0.1.0.dist-info/METADATA
ap2_sdk-0.1.0.dist-info/WHEEL
ap2_sdk-0.1.0.dist-info/top_level.txt
ap2_sdk-0.1.0.dist-info/RECORD
