Metadata-Version: 2.4
Name: ap2-sdk
Version: 0.1.0
Summary: Add your description here
Requires-Python: >=3.12
Requires-Dist: pebbling
Requires-Dist: pandas
Requires-Dist: twine>=6.2.0
